basesqlmodel/__init__.py
basesqlmodel/main.py
basesqlmodel/py.typed
basesqlmodel-0.1.0.dist-info/LICENSE
basesqlmodel-0.1.0.dist-info/WHEEL
basesqlmodel-0.1.0.dist-info/METADATA
basesqlmodel-0.1.0.dist-info/RECORD
