Metadata-Version: 2.1
Name: basesqlmodel
Version: 0.1.0
Summary: A very simple CRUD class for SQLModel! :sparkles:
Home-page: https://github.com/Kludex/basesqlmodel
License: MIT
Author: Marcelo Trylesinski
Author-email: marcelotryle@gmail.com
Requires-Python: >=3.8,<4.0
Classifier: Intended Audience :: Developers
Classifier: License :: OSI Approved :: MIT License
Classifier: Operating System :: OS Independent
Classifier: Programming Language :: Python
Classifier: Programming Language :: Python :: 3
Classifier: Programming Language :: Python :: 3 :: Only
Classifier: Programming Language :: Python :: 3.10
Classifier: Programming Language :: Python :: 3.8
Classifier: Programming Language :: Python :: 3.9
Classifier: Topic :: Software Development :: Libraries :: Python Modules
Requires-Dist: fastapi (>=0.68.1,<0.69.0)
Requires-Dist: sqlmodel (>=0.0.4,<0.0.5)
Project-URL: Repository, https://github.com/Kludex/basesqlmodel
